tms_django_router/__init__.py
tms_django_router/apps.py
tms_django_router/routers.py
tms_django_router-1.0.1.dist-info/METADATA
tms_django_router-1.0.1.dist-info/WHEEL
tms_django_router-1.0.1.dist-info/top_level.txt
tms_django_router-1.0.1.dist-info/RECORD
